llm_api_client/__init__.py
llm_api_client/_params.py
llm_api_client/_version.py
llm_api_client/api_client.py
llm_api_client/api_tracker.py
llm_api_client-0.1.3.dist-info/licenses/LICENSE
llm_api_client-0.1.3.dist-info/METADATA
llm_api_client-0.1.3.dist-info/WHEEL
llm_api_client-0.1.3.dist-info/top_level.txt
llm_api_client-0.1.3.dist-info/RECORD
