Metadata-Version: 2.4
Name: llm-api-client
Version: 0.1.3
Summary: A client for interacting with LLM completion APIs and tracking usage.
Author: Andre F. Cruz
License: MIT License
Project-URL: homepage, https://github.com/AndreFCruz/llm-api-client
Keywords: llm,api,client
Classifier: Development Status :: 3 - Alpha
Classifier: License :: OSI Approved :: MIT License
Classifier: Intended Audience :: Developers
Classifier: Topic :: Software Development :: Libraries :: Python Modules
Classifier: Topic :: Scientific/Engineering :: Artificial Intelligence
Classifier: Natural Language :: English
Classifier: Programming Language :: Python :: 3
Classifier: Programming Language :: Python :: 3.11
Classifier: Programming Language :: Python :: 3.12
Classifier: Programming Language :: Python :: 3.13
Requires-Python: >=3.11
License-File: LICENSE
Requires-Dist: litellm
Requires-Dist: openai<1.100
Requires-Dist: numpy
Requires-Dist: tqdm
Requires-Dist: pyrate-limiter>=3.0
Provides-Extra: tests
Requires-Dist: pytest>=8; extra == "tests"
Requires-Dist: coverage>=7; extra == "tests"
Requires-Dist: flake8-pyproject; extra == "tests"
Requires-Dist: flake8; extra == "tests"
Requires-Dist: mypy>=1.0; extra == "tests"
Requires-Dist: isort; extra == "tests"
Requires-Dist: pytest-xdist>=3; extra == "tests"
Dynamic: license-file
